montague/__init__.py
montague/exceptions.py
montague/ini.py
montague/loadwsgi.py
montague/logging.py
montague/structs.py
montague/testjson.py
montague/validation.py
montague/vendor/__init__.py
montague/vendor/pyramid_decorator.py
montague-0.2.1.dist-info/DESCRIPTION.rst
montague-0.2.1.dist-info/METADATA
montague-0.2.1.dist-info/metadata.json
montague-0.2.1.dist-info/RECORD
montague-0.2.1.dist-info/top_level.txt
montague-0.2.1.dist-info/WHEEL
