Metadata-Version: 2.0
Name: montague
Version: 0.2.1
Summary: Montague provides functions to load WSGI apps and servers based on configuration files. It's based on PasteDeploy's INI file support.
Home-page: https://github.com/inklesspen/montague
Author: Jon Rosebaugh
Author-email: jon@inklesspen.com
License: MIT
Platform: UNKNOWN
Classifier: Development Status :: 4 - Beta
Classifier: Intended Audience :: Developers
Classifier: License :: OSI Approved :: MIT License
Classifier: Operating System :: Unix
Classifier: Operating System :: POSIX
Classifier: Operating System :: Microsoft :: Windows
Classifier: Programming Language :: Python
Classifier: Programming Language :: Python :: 2.6
Classifier: Programming Language :: Python :: 2.7
Classifier: Programming Language :: Python :: 3
Classifier: Programming Language :: Python :: 3.3
Classifier: Programming Language :: Python :: 3.4
Classifier: Programming Language :: Python :: Implementation :: CPython
Classifier: Programming Language :: Python :: Implementation :: PyPy
Classifier: Topic :: Utilities
Requires-Dist: six (>=1.8.0)
Requires-Dist: characteristic (>=14.2.0)
